{
  "hash": "0a03f203",
  "configHash": "ca5b33f7",
  "lockfileHash": "ea0aaa1e",
  "browserHash": "79247b58",
  "optimized": {
    "vue": {
      "src": "../../../node_modules/vue/dist/vue.runtime.esm-bundler.js",
      "file": "vue.js",
      "fileHash": "a6be04cc",
      "needsInterop": false
    },
    "vitepress > @vue/devtools-api": {
      "src": "../../../node_modules/@vue/devtools-api/dist/index.js",
      "file": "vitepress___@vue_devtools-api.js",
      "fileHash": "47195c3c",
      "needsInterop": false
    },
    "vitepress > @vueuse/core": {
      "src": "../../../node_modules/@vueuse/core/index.mjs",
      "file": "vitepress___@vueuse_core.js",
      "fileHash": "cbcc6752",
      "needsInterop": false
    },
    "vitepress > @vueuse/integrations/useFocusTrap": {
      "src": "../../../node_modules/@vueuse/integrations/useFocusTrap.mjs",
      "file": "vitepress___@vueuse_integrations_useFocusTrap.js",
      "fileHash": "61c8e1f8",
      "needsInterop": false
    },
    "vitepress > mark.js/src/vanilla.js": {
      "src": "../../../node_modules/mark.js/src/vanilla.js",
      "file": "vitepress___mark__js_src_vanilla__js.js",
      "fileHash": "38c26843",
      "needsInterop": false
    },
    "vitepress > minisearch": {
      "src": "../../../node_modules/minisearch/dist/es/index.js",
      "file": "vitepress___minisearch.js",
      "fileHash": "637f6da4",
      "needsInterop": false
    },
    "@theme/index": {
      "src": "../../../node_modules/vitepress/dist/client/theme-default/index.js",
      "file": "@theme_index.js",
      "fileHash": "b1f66553",
      "needsInterop": false
    }
  },
  "chunks": {
    "chunk-ECKPOFXB": {
      "file": "chunk-ECKPOFXB.js"
    },
    "chunk-W6V53FDX": {
      "file": "chunk-W6V53FDX.js"
    }
  }
}